v_installer/__init__.py
v_installer/cli.py
v_installer/gui.py
v_installer/package_version.txt
v_installer-0.0.34.dist-info/LICENSE
v_installer-0.0.34.dist-info/METADATA
v_installer-0.0.34.dist-info/WHEEL
v_installer-0.0.34.dist-info/entry_points.txt
v_installer-0.0.34.dist-info/top_level.txt
v_installer-0.0.34.dist-info/RECORD
