Metadata-Version: 2.1
Name: v-installer
Version: 0.0.34
Summary: Install my app, not for all people
Home-page: http://gitea:8000/datlt4/fortifai_monitoring
Author: Koi
Author-email: your.email@example.com
Classifier: Programming Language :: Python :: 3
Classifier: License :: OSI Approved :: MIT License
Classifier: Operating System :: OS Independent
Requires-Python: >=3.6
License-File: LICENSE
Requires-Dist: requests
Requires-Dist: textual (==0.89.1)
Requires-Dist: textual-dev (==1.7.0)
